{
  "time": "22/3/2025, 00:07:45",
  "totalVotes": 100,
  "countedVotes": 175,
  "invalidVotes": 4,
  "members": [
    {
      "no": 1,
      "votes": 103,
      "rank": 4,
      "team": "A"
    },
    {
      "no": 2,
      "votes": 112,
      "rank": 1,
      "team": "B"
    },
    {
      "no": 3,
      "votes": 105,
      "rank": 3,
      "team": "A"
    },
    {
      "no": 4,
      "votes": 96,
      "rank": 9,
      "team": "B"
    },
    {
      "no": 5,
      "votes": 87,
      "rank": 13,
      "team": "A"
    },
    {
      "no": 6,
      "votes": 102,
      "rank": 5,
      "team": "A"
    },
    {
      "no": 7,
      "votes": 85,
      "rank": 14,
      "team": "B"
    },
    {
      "no": 8,
      "votes": 98,
      "rank": 7,
      "team": "A"
    },
    {
      "no": 9,
      "votes": 92,
      "rank": 12,
      "team": "A"
    },
    {
      "no": 10,
      "votes": 94,
      "rank": 11,
      "team": "B"
    },
    {
      "no": 11,
      "votes": 97,
      "rank": 8,
      "team": "A"
    },
    {
      "no": 12,
      "votes": 64,
      "rank": 18,
      "team": "B"
    },
    {
      "no": 13,
      "votes": 49,
      "rank": 22,
      "team": "B"
    },
    {
      "no": 14,
      "votes": 64,
      "rank": 18,
      "team": "B"
    },
    {
      "no": 15,
      "votes": 59,
      "rank": 20,
      "team": "A"
    },
    {
      "no": 16,
      "votes": 71,
      "rank": 16,
      "team": "A"
    },
    {
      "no": 17,
      "votes": 57,
      "rank": 21,
      "team": "B"
    },
    {
      "no": 18,
      "votes": 76,
      "rank": 15,
      "team": "B"
    },
    {
      "no": 19,
      "votes": 95,
      "rank": 10,
      "team": "A"
    },
    {
      "no": 20,
      "votes": 109,
      "rank": 2,
      "team": "B"
    },
    {
      "no": 21,
      "votes": 66,
      "rank": 17,
      "team": "A"
    },
    {
      "no": 22,
      "votes": 100,
      "rank": 6,
      "team": "B"
    }
  ]
}